README.md
setup.cfg
setup.py
code128cgen/__init__.py
code128cgen.egg-info/PKG-INFO
code128cgen.egg-info/SOURCES.txt
code128cgen.egg-info/dependency_links.txt
code128cgen.egg-info/requires.txt
code128cgen.egg-info/top_level.txt