Metadata-Version: 2.1
Name: code128cgen
Version: 0.0.2
Summary: Generation of the Code128c barcode
Home-page: https://github.com/damiandennis/code128cgen
Author: Damian Dennis
Author-email: damiandennis@gmail.com
License: UNKNOWN
Platform: UNKNOWN
Requires-Python: >=3.6
